{"Data_Cruda": [{"IDTAG": 105, "REGISTRO_1": 0, "REGISTRO_2": 16384, "TIMESTAMP": "2021-11-01 23:13:15", "INDEXADO": false, "DIRECCIONCAMPO": "101", "TAG_ADDRES": 100}, {"IDTAG": 106, "REGISTRO_1": 0, "REGISTRO_2": 0, "TIMESTAMP": "2021-11-01 23:13:18", "INDEXADO": false, "DIRECCIONCAMPO": "103", "TAG_ADDRES": 102}, {"IDTAG": 107, "REGISTRO_1": 0, "REGISTRO_2": 0, "TIMESTAMP": "2021-11-01 23:13:21", "INDEXADO": false, "DIRECCIONCAMPO": "105", "TAG_ADDRES": 104}, {"IDTAG": 108, "REGISTRO_1": 0, "REGISTRO_2": 0, "TIMESTAMP": "2021-11-01 23:13:21", "INDEXADO": false, "DIRECCIONCAMPO": "107", "TAG_ADDRES": 106}, {"IDTAG": 109, "REGISTRO_1": 0, "REGISTRO_2": 0, "TIMESTAMP": "2021-11-01 23:13:21", "INDEXADO": false, "DIRECCIONCAMPO": "109", "TAG_ADDRES": 108}, {"IDTAG": 110, "REGISTRO_1": 0, "REGISTRO_2": 0, "TIMESTAMP": "2021-11-01 23:13:21", "INDEXADO": false, "DIRECCIONCAMPO": "111", "TAG_ADDRES": 110}, {"IDTAG": 111, "REGISTRO_1": 0, "REGISTRO_2": 0, "TIMESTAMP": "2021-11-01 23:13:21", "INDEXADO": false, "DIRECCIONCAMPO": "113", "TAG_ADDRES": 112}, {"IDTAG": 112, "REGISTRO_1": 0, "REGISTRO_2": 0, "TIMESTAMP": "2021-11-01 23:13:21", "INDEXADO": false, "DIRECCIONCAMPO": "115", "TAG_ADDRES": 114}]}