{"31": {"TANQUE": "tk6", "LT": "0.0", "LT_PORCENTAJE": "0.0", "IDTOV": 170, "IDNSV": 172, "IDGSV": 171, "IDLT": 165, "TOV": "10.0", "TOV_UNIDAD": "bls", "GSV": "10.0", "GSV_UNIDAD": "bls", "NSV": "10.0", "NSV_UNIDAD": "bls", "LT_UNIDAD": "m", "VALORMAXIMO": 19.226, "VALORMINIMO": 0.0, "LT_ALARMA": "C", "TOV_ALARMA": "C", "NSV_ALARMA": "C", "GSV_ALARMA": "C", "TIMESTAMP_lt": "2021-08-01 23:51:57", "TIMESTAMP_TOV": "2021-08-01 23:51:58", "TIMESTAMP_GSV": "2021-08-01 23:51:58", "TIMESTAMP_NSV": "2021-08-01 23:51:58", "IDPT": 166, "PT_UNIDAD": "psi", "PT": "0.0", "PT_ALARMA": "C", "TIMESTAMP_pt": "2021-08-01 23:51:57", "IDTT": 167, "TT_UNIDAD": "f", "TT": "0.0", "TT_ALARMA": "C", "TIMESTAMP_tt": "2021-08-01 23:51:57", "IDLTA": 168, "LTA_UNIDAD": "m", "LTA": "0.0", "LTA_ALARMA": "C", "TIMESTAMP_lta": "2021-08-01 23:51:57", "IDAYS": 169, "AYS_UNIDAD": "%", "AYS": "0.0", "AYS_ALARMA": "C", "TIMESTAMP_ays": "2021-08-01 23:51:57"}, "29": {"TANQUE": "tk4", "LT": "0.0", "LT_PORCENTAJE": "0.0", "IDTOV": 154, "IDNSV": 156, "IDGSV": 155, "IDLT": 149, "TOV": "10.0", "TOV_UNIDAD": "bls", "GSV": "10.0", "GSV_UNIDAD": "bls", "NSV": "10.0", "NSV_UNIDAD": "bls", "LT_UNIDAD": "m", "VALORMAXIMO": 19.226, "VALORMINIMO": 0.0, "LT_ALARMA": "C", "TOV_ALARMA": "C", "NSV_ALARMA": "C", "GSV_ALARMA": "C", "TIMESTAMP_lt": "2021-08-01 23:52:09", "TIMESTAMP_TOV": "2021-08-01 23:52:10", "TIMESTAMP_GSV": "2021-08-01 23:52:10", "TIMESTAMP_NSV": "2021-08-01 23:52:10", "IDPT": 150, "PT_UNIDAD": "psi", "PT": "0.0", "PT_ALARMA": "C", "TIMESTAMP_pt": "2021-08-01 23:52:09", "IDTT": 151, "TT_UNIDAD": "f", "TT": "0.0", "TT_ALARMA": "C", "TIMESTAMP_tt": "2021-08-01 23:52:09", "IDLTA": 152, "LTA_UNIDAD": "m", "LTA": "0.0", "LTA_ALARMA": "C", "TIMESTAMP_lta": "2021-08-01 23:52:09", "IDAYS": 153, "AYS_UNIDAD": "D", "AYS": "0.0", "AYS_ALARMA": "C", "TIMESTAMP_ays": "2021-08-01 23:52:09"}, "28": {"TANQUE": "tk3", "LT": "0.0", "LT_PORCENTAJE": "0.0", "IDTOV": 146, "IDNSV": 148, "IDGSV": 147, "IDLT": 141, "TOV": "10.0", "TOV_UNIDAD": "bls", "GSV": "10.0", "GSV_UNIDAD": "bls", "NSV": "10.0", "NSV_UNIDAD": "bls", "LT_UNIDAD": "m", "VALORMAXIMO": 19.226, "VALORMINIMO": 0.0, "LT_ALARMA": "C", "TOV_ALARMA": "C", "NSV_ALARMA": "C", "GSV_ALARMA": "C", "TIMESTAMP_lt": "2021-08-01 23:51:51", "TIMESTAMP_TOV": "2021-08-01 23:51:52", "TIMESTAMP_GSV": "2021-08-01 23:51:52", "TIMESTAMP_NSV": "2021-08-01 23:51:52", "IDPT": 142, "PT_UNIDAD": "C", "PT": "0.0", "PT_ALARMA": "C", "TIMESTAMP_pt": "2021-08-01 23:51:51", "IDTT": 143, "TT_UNIDAD": "f", "TT": "0.0", "TT_ALARMA": "C", "TIMESTAMP_tt": "2021-08-01 23:51:51", "IDLTA": 144, "LTA_UNIDAD": "m", "LTA": "0.0", "LTA_ALARMA": "C", "TIMESTAMP_lta": "2021-08-01 23:51:51", "IDAYS": 145, "AYS_UNIDAD": "%", "AYS": "0.0", "AYS_ALARMA": "C", "TIMESTAMP_ays": "2021-08-01 23:51:51"}, "30": {"TANQUE": "tk5", "LT": "0.0", "LT_PORCENTAJE": "0.0", "IDTOV": 162, "IDNSV": 164, "IDGSV": 163, "IDLT": 157, "TOV": "10.0", "TOV_UNIDAD": "bls", "GSV": "10.0", "GSV_UNIDAD": "bls", "NSV": "10.0", "NSV_UNIDAD": "bls", "LT_UNIDAD": "m", "VALORMAXIMO": 19.226, "VALORMINIMO": 0.0, "LT_ALARMA": "C", "TOV_ALARMA": "C", "NSV_ALARMA": "C", "GSV_ALARMA": "C", "TIMESTAMP_lt": "2021-08-01 23:52:07", "TIMESTAMP_TOV": "2021-08-01 23:52:08", "TIMESTAMP_GSV": "2021-08-01 23:52:08", "TIMESTAMP_NSV": "2021-08-01 23:52:08", "IDPT": 158, "PT_UNIDAD": "psi", "PT": "0.0", "PT_ALARMA": "C", "TIMESTAMP_pt": "2021-08-01 23:52:07", "IDTT": 159, "TT_UNIDAD": "f", "TT": "0.0", "TT_ALARMA": "C", "TIMESTAMP_tt": "2021-08-01 23:52:07", "IDLTA": 160, "LTA_UNIDAD": "m", "LTA": "0.0", "LTA_ALARMA": "C", "TIMESTAMP_lta": "2021-08-01 23:52:07", "IDAYS": 161, "AYS_UNIDAD": "%", "AYS": "0.0", "AYS_ALARMA": "C", "TIMESTAMP_ays": "2021-08-01 23:52:07"}, "26": {"TANQUE": "tk1", "LT": "0.0", "LT_PORCENTAJE": "0.0", "IDTOV": 130, "IDNSV": 132, "IDGSV": 131, "IDLT": 125, "TOV": "10.0", "TOV_UNIDAD": "bls", "GSV": "10.0", "GSV_UNIDAD": "bls", "NSV": "10.0", "NSV_UNIDAD": "bls", "LT_UNIDAD": "m", "VALORMAXIMO": 19.226, "VALORMINIMO": 0.0, "LT_ALARMA": "C", "TOV_ALARMA": "C", "NSV_ALARMA": "C", "GSV_ALARMA": "C", "TIMESTAMP_lt": "2021-08-01 23:51:59", "TIMESTAMP_TOV": "2021-08-01 23:52:00", "TIMESTAMP_GSV": "2021-08-01 23:52:00", "TIMESTAMP_NSV": "2021-08-01 23:52:00", "IDPT": 126, "PT_UNIDAD": "psi", "PT": "0.0", "PT_ALARMA": "C", "TIMESTAMP_pt": "2021-08-01 23:51:59", "IDTT": 127, "TT_UNIDAD": "f", "TT": "0.0", "TT_ALARMA": "C", "TIMESTAMP_tt": "2021-08-01 23:51:59", "IDLTA": 128, "LTA_UNIDAD": "A", "LTA": "0.0", "LTA_ALARMA": "C", "TIMESTAMP_lta": "2021-08-01 23:51:59", "IDAYS": 129, "AYS_UNIDAD": "%", "AYS": "0.0", "AYS_ALARMA": "C", "TIMESTAMP_ays": "2021-08-01 23:51:59"}}